novella_research/__init__.py
novella_research/activations/__init__.py
novella_research/activations/flux.py
novella_research-0.1.4.dist-info/METADATA
novella_research-0.1.4.dist-info/WHEEL
novella_research-0.1.4.dist-info/top_level.txt
novella_research-0.1.4.dist-info/RECORD
