Metadata-Version: 2.1
Name: novella_research
Version: 0.1.4
Summary: This package contains all my custom Tensorflow work.
Home-page: https://github.com/yourusername/novella_research
Author: Joshua Kim
Author-email: happyjoshua08@gmail.com
Classifier: Programming Language :: Python :: 3
Classifier: Programming Language :: Python :: 3.7
Classifier: License :: OSI Approved :: MIT License
Classifier: Operating System :: OS Independent
Requires-Python: >=3.6
Requires-Dist: tensorflow>=2.0
